sinapsis_anomalib/__init__.py
sinapsis_anomalib/helpers/__init__.py
sinapsis_anomalib/helpers/config_factory.py
sinapsis_anomalib/helpers/configs.py
sinapsis_anomalib/helpers/env_var_keys.py
sinapsis_anomalib/helpers/tags.py
sinapsis_anomalib/templates/__init__.py
sinapsis_anomalib/templates/anomalib_base.py
sinapsis_anomalib/templates/anomalib_base_inference.py
sinapsis_anomalib/templates/anomalib_export.py
sinapsis_anomalib/templates/anomalib_openvino_inference.py
sinapsis_anomalib/templates/anomalib_torch_inference.py
sinapsis_anomalib/templates/anomalib_train.py
sinapsis_anomalib-0.1.14.dist-info/licenses/LICENSE
sinapsis_anomalib-0.1.14.dist-info/METADATA
sinapsis_anomalib-0.1.14.dist-info/WHEEL
sinapsis_anomalib-0.1.14.dist-info/top_level.txt
sinapsis_anomalib-0.1.14.dist-info/RECORD
