Metadata-Version: 2.4
Name: sinapsis-anomalib
Version: 0.1.14
Summary: Templates for anomaly detection with computer vision using anomalib library.
Author-email: SinapsisAI <dev@sinapsis.tech>
Project-URL: Homepage, https://sinapsis.tech
Project-URL: Documentation, https://docs.sinapsis.tech/docs
Project-URL: Tutorials, https://docs.sinapsis.tech/tutorials
Project-URL: Repository, https://github.com/Sinapsis-AI/sinapsis-anomaly-detection.git
Requires-Python: >=3.10
License-File: LICENSE
Requires-Dist: torch>=2.5.1
Requires-Dist: einops>=0.8.0
Requires-Dist: freia>=0.2
Requires-Dist: imgaug>=0.4.0
Requires-Dist: kornia>=0.7.4
Requires-Dist: matplotlib==3.9.0
Requires-Dist: nncf>=2.14.0
Requires-Dist: numpy==1.26.4
Requires-Dist: onnx>=1.17.0
Requires-Dist: opencv-python>=4.10.0.84
Requires-Dist: openvino>=2024.5.0
Requires-Dist: pandas>=2.2.3
Requires-Dist: psutil>=6.1.0
Requires-Dist: scikit-learn>=1.5.2
Requires-Dist: sinapsis>=0.1.1
Requires-Dist: dotenv>=0.9.9
Requires-Dist: anomalib>=2.0.0
Requires-Dist: torchvision>=0.20.1
Requires-Dist: timm>=1.0.15
Requires-Dist: open-clip-torch>=2.31.0
Requires-Dist: lightning>=2.4.1
Provides-Extra: vlm
Requires-Dist: python-dotenv>=1.0.1; extra == "vlm"
Requires-Dist: transformers>=4.45.0; extra == "vlm"
Requires-Dist: openai>=1.50.0; extra == "vlm"
Requires-Dist: ollama>=0.4.7; extra == "vlm"
Provides-Extra: loggers
Requires-Dist: comet>=3.1.0; extra == "loggers"
Requires-Dist: mlflow>=2.19.0; extra == "loggers"
Requires-Dist: tensorboard>=2.18.0; extra == "loggers"
Requires-Dist: wandb>=0.19.1; extra == "loggers"
Provides-Extra: all
Requires-Dist: sinapsis-anomalib[loggers,vlm]; extra == "all"
Dynamic: license-file
